ngoci/__init__.py
ngoci/environment.py
ngoci/project.py
ngoci/project_loader.py
ngoci/project_premake5.py
ngoci/python_environment.py
ngoci/schemas/cookiecutter.json
ngoci/schemas/environment.json
ngoci/schemas/project.json
ngoci/schemas/project_loader.json
ngoci/schemas/python_environment.json
ngoci/templates/premake5.lua
ngoci/templates/template - eclipse.lnk
ngoci/transforms/cookiecutter2project.mtm
ngoci-0.1.2.dist-info/METADATA
ngoci-0.1.2.dist-info/RECORD
ngoci-0.1.2.dist-info/WHEEL
ngoci-0.1.2.dist-info/entry_points.txt
ngoci-0.1.2.dist-info/top_level.txt
