Metadata-Version: 2.1
Name: ngoci
Version: 0.1.2
Summary: Utilities for continuous integration, development workflow, and package management
Home-page: https://github.com/numengo/python-ngoci
Author: ('C\xc3\xa9dric ROMAN',)
Author-email: roman@numengo.com
License: GNU General Public License v3
Keywords: continuous integration, project management, build steps, hooks, docker, test suite
Platform: UNKNOWN
Classifier: Development Status :: 3 - Alpha
Classifier: Intended Audience :: Developers
Classifier: License :: OSI Approved :: GNU General Public License v3 (GPLv3)
Classifier: Operating System :: Unix
Classifier: Operating System :: POSIX
Classifier: Operating System :: Microsoft :: Windows
Classifier: Programming Language :: Python
Classifier: Programming Language :: Python :: 2.7
Classifier: Programming Language :: Python :: 3
Classifier: Programming Language :: Python :: 3.3
Classifier: Programming Language :: Python :: 3.4
Classifier: Programming Language :: Python :: 3.5
Classifier: Programming Language :: Python :: 3.6
Classifier: Programming Language :: Python :: Implementation :: CPython
Classifier: Programming Language :: Python :: Implementation :: PyPy
Classifier: Topic :: Utilities
Requires: pathlib
Requires: apipkg
Requires: future
Requires: click
Requires: ngofile
Requires: tox
Requires: isort
Requires: yapf
Requires: autoflake
Requires: bumpversion
Requires: twine
Requires: docker
Requires-Dist: pathlib
Requires-Dist: apipkg
Requires-Dist: future
Requires-Dist: click
Requires-Dist: ngofile
Requires-Dist: tox
Requires-Dist: isort
Requires-Dist: yapf
Requires-Dist: autoflake
Requires-Dist: bumpversion
Requires-Dist: twine
Requires-Dist: docker
